Metadata-Version: 2.1
Name: deflate-dict
Version: 1.2.2
Summary: Package to deflate and inflate dictionaries.
Home-page: https://github.com/LucaCappelletti94/deflate_dict
Author: Luca Cappelletti
Author-email: cappelletti.luca94@gmail.com
License: MIT
Platform: UNKNOWN
Classifier: Development Status :: 5 - Production/Stable
Classifier: License :: OSI Approved :: MIT License
Classifier: Programming Language :: Python :: 3
Provides-Extra: test
License-File: LICENSE
